Led_T1.v
module Exe01(

	input clk,
	output s);


	assign s = clk;
	
endmodule
	
module teste;
	
	reg clk;
	always #3 clk <= ~clk;
	
	wire s;
	
	Exe01 e(clk, s);
	
	initial begin
	$dumpvars(0, e);
	#1
	clk = 1;
	#500;
	$finish;

	end
endmodule

Led T1/dump.vcd
$date
	Fri Mar  4 13:42:29 2016
$end
$version
	Icarus Verilog
$end
$timescale
	1s
$end
$scope module teste $end
$scope module e $end
$var wire 1 ! clk $end
$var wire 1 " s $end
$upscope $end
$upscope $end
$enddefinitions $end
#0
$dumpvars
x"
x!
$end
#1
1"
1!
#3
0"
0!
#6
1"
1!
#9
0"
0!
#12
1"
1!
#15
0"
0!
#18
1"
1!
#21
0"
0!
#24
1"
1!
#27
0"
0!
#30
1"
1!
#33
0"
0!
#36
1"
1!
#39
0"
0!
#42
1"
1!
#45
0"
0!
#48
1"
1!
#51
0"
0!
#54
1"
1!
#57
0"
0!
#60
1"
1!
#63
0"
0!
#66
1"
1!
#69
0"
0!
#72
1"
1!
#75
0"
0!
#78
1"
1!
#81
0"
0!
#84
1"
1!
#87
0"
0!
#90
1"
1!
#93
0"
0!
#96
1"
1!
#99
0"
0!
#102
1"
1!
#105
0"
0!
#108
1"
1!
#111
0"
0!
#114
1"
1!
#117
0"
0!
#120
1"
1!
#123
0"
0!
#126
1"
1!
#129
0"
0!
#132
1"
1!
#135
0"
0!
#138
1"
1!
#141
0"
0!
#144
1"
1!
#147
0"
0!
#150
1"
1!
#153
0"
0!
#156
1"
1!
#159
0"
0!
#162
1"
1!
#165
0"
0!
#168
1"
1!
#171
0"
0!
#174
1"
1!
#177
0"
0!
#180
1"
1!
#183
0"
0!
#186
1"
1!
#189
0"
0!
#192
1"
1!
#195
0"
0!
#198
1"
1!
#201
0"
0!
#204
1"
1!
#207
0"
0!
#210
1"
1!
#213
0"
0!
#216
1"
1!
#219
0"
0!
#222
1"
1!
#225
0"
0!
#228
1"
1!
#231
0"
0!
#234
1"
1!
#237
0"
0!
#240
1"
1!
#243
0"
0!
#246
1"
1!
#249
0"
0!
#252
1"
1!
#255
0"
0!
#258
1"
1!
#261
0"
0!
#264
1"
1!
#267
0"
0!
#270
1"
1!
#273
0"
0!
#276
1"
1!
#279
0"
0!
#282
1"
1!
#285
0"
0!
#288
1"
1!
#291
0"
0!
#294
1"
1!
#297
0"
0!
#300
1"
1!
#303
0"
0!
#306
1"
1!
#309
0"
0!
#312
1"
1!
#315
0"
0!
#318
1"
1!
#321
0"
0!
#324
1"
1!
#327
0"
0!
#330
1"
1!
#333
0"
0!
#336
1"
1!
#339
0"
0!
#342
1"
1!
#345
0"
0!
#348
1"
1!
#351
0"
0!
#354
1"
1!
#357
0"
0!
#360
1"
1!
#363
0"
0!
#366
1"
1!
#369
0"
0!
#372
1"
1!
#375
0"
0!
#378
1"
1!
#381
0"
0!
#384
1"
1!
#387
0"
0!
#390
1"
1!
#393
0"
0!
#396
1"
1!
#399
0"
0!
#402
1"
1!
#405
0"
0!
#408
1"
1!
#411
0"
0!
#414
1"
1!
#417
0"
0!
#420
1"
1!
#423
0"
0!
#426
1"
1!
#429
0"
0!
#432
1"
1!
#435
0"
0!
#438
1"
1!
#441
0"
0!
#444
1"
1!
#447
0"
0!
#450
1"
1!
#453
0"
0!
#456
1"
1!
#459
0"
0!
#462
1"
1!
#465
0"
0!
#468
1"
1!
#471
0"
0!
#474
1"
1!
#477
0"
0!
#480
1"
1!
#483
0"
0!
#486
1"
1!
#489
0"
0!
#492
1"
1!
#495
0"
0!
#498
1"
1!
#501
0"
0!
